{"1":{"i":["nan"],"p":{}},"10/369":{"i":["nan"],"p":{}},"10/374XR":{"i":["nan"],"p":{}},"15":{"i":["nan"],"p":{}},"18":{"i":["nan"],"p":{}},"2":{"i":["nan"],"p":{}},"20":{"i":["nan"],"p":{}},"21":{"i":["nan"],"p":{}},"25":{"i":["nan"],"p":{}},"26":{"i":["nan"],"p":{}},"27":{"i":["nan"],"p":{}},"28":{"i":["nan"],"p":{}},"29":{"i":["nan"],"p":{}},"30":{"i":["nan"],"p":{}},"32":{"i":["nan"],"p":{}},"33":{"i":["nan"],"p":{}},"35":{"i":["nan"],"p":{}},"36":{"i":["nan"],"p":{}},"369":{"i":["nan"],"p":{}},"37":{"i":["nan"],"p":{}},"40":{"i":["nan"],"p":{}},"42":{"i":["nan"],"p":{}},"43":{"i":["nan"],"p":{}},"46":{"i":["nan"],"p":{}},"47":{"i":["nan"],"p":{}},"50":{"i":["nan"],"p":{}},"52":{"i":["nan"],"p":{}},"56":{"i":["nan"],"p":{}},"57":{"i":["nan"],"p":{}},"59":{"i":["nan"],"p":{}},"6/374":{"i":["nan"],"p":{}},"60":{"i":["nan"],"p":{}},"64":{"i":["nan"],"p":{}},"7":{"i":["nan"],"p":{}},"9":{"i":["nan"],"p":{}},"אביגדור":{"i":["nan","1","10","102","11","111","111א","116","12","13","13א","14","15","15ג","16א","16ב","18","18ב","19","19א","1א","20","201","202","203","204","205","206","208","209","21","211","212","213","214","215","216","217","218","219","22","220","221","222","223","224","225","226","226ג","227","228","229","23","230","231","232","233","234","235","236","237","238","239","23ב","24","240","241","242","243","244","245","246","247","248","249","25","250","251","252","253","254","255","256","257","258","259","26","260","261","262","263","264","265","27","28","29","3","303","304","305","306","308","309","31","310","311","316","317","318","319","32","322","33","34","34א","34ב","39","3א","4","40","40א","41","48","49","49א","5","50","50ב","51","51א","51ב","52","53","534","53א","54","55","56","57","58","61","62","63","63א","64","65","7","7ב","80","84","8א","8ג","9"],"p":{}},"אביגדור 29":{"i":["nan"],"p":{}},"אביגדור 41":{"i":["nan"],"p":{}},"אביגדור 42":{"i":["nan"],"p":{}},"אביגדור 7":{"i":["nan"],"p":{}},"אביגדור ארון סעף בפילר עמוד 36":{"i":["nan"],"p":{}},"אביגדור ארון סעף בפילר עמוד A35":{"i":["nan"],"p":{}},"אביגדור מגרש מגרש ספורט":{"i":["nan"],"p":{}},"אביגדור מרפאה מרפאה":{"i":["nan"],"p":{}},"אביגדור קלסטר 752":{"i":["nan"],"p":{}},"אביגדור ת רחוב ע\"מ 369":{"i":["nan"],"p":{}},"ב":{"i":["nan"],"p":{}},"ב60":{"i":["nan"],"p":{}},"החלוץ":{"i":["11"],"p":{}},"ח27/369/":{"i":["nan"],"p":{}},"מאגד NGN קלסטר 736":{"i":["nan"],"p":{}},"מועדון נוער":{"i":["nan"],"p":{}},"מחלבה":{"i":["nan"],"p":{}},"משק 40 אצל יואל אביגד":{"i":["nan"],"p":{}},"צומת כניסה לאביגדור":{"i":["nan"],"p":{}},"צומת כפר ורבורג":{"i":["nan"],"p":{}}}