{"1/220R":{"i":["nan"],"p":{}},"1פ-2/216R":{"i":["nan"],"p":{}},"2/216R":{"i":["nan"],"p":{}},"211R":{"i":["nan"],"p":{}},"3/212R":{"i":["nan"],"p":{}},"AH100":{"i":["nan"],"p":{}},"AH104":{"i":["nan"],"p":{}},"AH107":{"i":["nan"],"p":{}},"AH108":{"i":["nan"],"p":{}},"AH110":{"i":["nan"],"p":{}},"AH118":{"i":["nan"],"p":{}},"AH120":{"i":["nan"],"p":{}},"AH130":{"i":["nan"],"p":{}},"AH132":{"i":["nan"],"p":{}},"AH140":{"i":["nan"],"p":{}},"AH141":{"i":["nan"],"p":{}},"R402 מ\"ג.":{"i":["nan"],"p":{}},"R612/2 הזנה ישירה":{"i":["nan"],"p":{}},"R812/2 דרך מניה מ\"ג":{"i":["nan"],"p":{}},"א.ח.041":{"i":["nan"],"p":{}},"אילון R/215":{"i":[],"p":{"nan":"1"}},"nan":{"i":[],"p":{"nan":"1","92":"1"}},"אילון AH130":{"i":[],"p":{"nan":"1"}},"אילון 50":{"i":[],"p":{"nan":"2"}}}