{"1/210A":{"i":["nan"],"p":{}},"10/9rn":{"i":["nan"],"p":{}},"129":{"i":["nan"],"p":{}},"49":{"i":["nan"],"p":{}},"51":{"i":["nan"],"p":{}},"65/94R":{"i":["nan"],"p":{}},"91":{"i":["nan"],"p":{}},"99":{"i":["nan"],"p":{}},"AH 116":{"i":["nan"],"p":{}},"AH100":{"i":["nan"],"p":{}},"AH100 מגורים":{"i":["1070"],"p":{}},"AH102":{"i":["nan"],"p":{}},"AH110":{"i":["nan"],"p":{}},"AH111":{"i":["nan"],"p":{}},"AH112":{"i":["nan"],"p":{}},"AH117":{"i":["nan"],"p":{}},"AH118":{"i":["nan"],"p":{}},"א.ח 112 מגורים":{"i":["1035"],"p":{}},"א.ח 116 הרחבה":{"i":["nan"],"p":{}},"אשרת":{"i":["nan","1","100ב","102","13","14","18","180","2","207","23","252","257","3","321","69","70","71","73","75","80","91","96","97","98"],"p":{}},"אשרת - מושב":{"i":["1"],"p":{}},"אשרת 55":{"i":["nan"],"p":{}},"אשרת מערב":{"i":["nan"],"p":{}},"מחצבת אושרת":{"i":["nan"],"p":{}}}