{"AH31מ\"ג":{"i":["nan"],"p":{}},"---":{"i":["nan"],"p":{}},"1/235A":{"i":["nan"],"p":{}},"1/355A":{"i":["nan"],"p":{}},"11/944R":{"i":["nan"],"p":{}},"12/396A":{"i":["nan"],"p":{}},"13":{"i":["nan"],"p":{}},"182/447R":{"i":["nan"],"p":{}},"1MT":{"i":["nan"],"p":{}},"200R":{"i":["nan"],"p":{}},"267/212R":{"i":["nan"],"p":{}},"3":{"i":["nan"],"p":{}},"50/42XR":{"i":["nan"],"p":{}},"70/178R":{"i":["nan"],"p":{}},"75/178R":{"i":["nan"],"p":{}},"80/178R":{"i":["nan"],"p":{}},"92/447R":{"i":["nan"],"p":{}},"925R":{"i":["nan"],"p":{}},"תחנת שידור":{"i":["nan"],"p":{}}}