{"1/1478V":{"i":[""],"p":{}},"1/471":{"i":[""],"p":{}},"109":{"i":[""],"p":{}},"123":{"i":[""],"p":{}},"125":{"i":[""],"p":{}},"126":{"i":[""],"p":{}},"133":{"i":[""],"p":{}},"138":{"i":[""],"p":{}},"142":{"i":[""],"p":{}},"16":{"i":[""],"p":{}},"18":{"i":[""],"p":{}},"25":{"i":[""],"p":{}},"29":{"i":[""],"p":{}},"31":{"i":[""],"p":{}},"31B":{"i":[""],"p":{}},"32":{"i":[""],"p":{}},"45":{"i":[""],"p":{}},"52":{"i":[""],"p":{}},"53":{"i":[""],"p":{}},"54":{"i":[""],"p":{}},"63":{"i":[""],"p":{}},"7/481XV":{"i":[""],"p":{}},"70":{"i":[""],"p":{}},"71":{"i":[""],"p":{}},"81":{"i":[""],"p":{}},"87":{"i":[""],"p":{}},"89":{"i":[""],"p":{}},"9/481XV":{"i":[""],"p":{}},"91":{"i":[""],"p":{}},"95":{"i":[""],"p":{}},"AH2":{"i":[""],"p":{}},"AH3":{"i":[""],"p":{}},"AH6":{"i":[""],"p":{}},"AH8":{"i":[""],"p":{}},"V424 מ\"ג":{"i":[""],"p":{}}}