{"1/220R":{"i":["nan"],"p":{}},"10":{"i":["nan"],"p":{}},"10/229R":{"i":["nan"],"p":{}},"105":{"i":["nan"],"p":{}},"11/221R":{"i":["nan"],"p":{}},"12A":{"i":["nan"],"p":{}},"153":{"i":["nan"],"p":{}},"154":{"i":["nan"],"p":{}},"157":{"i":["nan"],"p":{}},"16":{"i":["nan"],"p":{}},"175":{"i":["nan"],"p":{}},"18":{"i":["nan"],"p":{}},"19":{"i":["nan"],"p":{}},"1פ-2/220R":{"i":["nan"],"p":{}},"1פ-20/229R":{"i":["nan"],"p":{}},"1פ-3/229R":{"i":["nan"],"p":{}},"1פ-RX922/3":{"i":["nan"],"p":{}},"20/221R":{"i":["nan"],"p":{}},"21":{"i":["nan"],"p":{}},"227Rמ\"ג":{"i":["nan"],"p":{}},"23":{"i":["nan"],"p":{}},"2X1/61XMA":{"i":["nan"],"p":{}},"3/227XR":{"i":["nan"],"p":{}},"3/45MA":{"i":["nan"],"p":{}},"30":{"i":["nan"],"p":{}},"35":{"i":["nan"],"p":{}},"38":{"i":["nan"],"p":{}},"42":{"i":["nan"],"p":{}},"54":{"i":["nan"],"p":{}},"9":{"i":["nan"],"p":{}},"AH100":{"i":["nan"],"p":{}},"AH101":{"i":["nan"],"p":{}},"AH150":{"i":["nan"],"p":{}},"AH200":{"i":["nan"],"p":{}},"אוסם הגליל":{"i":["nan"],"p":{}},"אלוין":{"i":["nan"],"p":{}},"גורן":{"i":["nan"],"p":{}},"קידוח גורן 1":{"i":["nan"],"p":{}},"תחט\"פ ניצן":{"i":["4363"],"p":{}},"nan":{"i":[],"p":{"nan":"1"}},"גורן 19":{"i":[],"p":{"nan":"1"}},"גורן 161":{"i":[],"p":{"nan":"1"}},"גורן 157":{"i":[],"p":{"nan":"1"}},"גורן 153":{"i":[],"p":{"nan":"1"}}}