{"192/9ZY":{"i":["nan","nan"],"p":{}},"1001":{"i":["nan"],"p":{}},"101C":{"i":["nan"],"p":{}},"1020":{"i":["nan"],"p":{}},"1024":{"i":["nan"],"p":{}},"1028":{"i":["nan"],"p":{}},"1029":{"i":["nan"],"p":{}},"1049":{"i":["nan"],"p":{}},"1050":{"i":["nan"],"p":{}},"1052":{"i":["nan"],"p":{}},"1058":{"i":["nan"],"p":{}},"1059":{"i":["nan"],"p":{}},"1081":{"i":["nan"],"p":{}},"1082A":{"i":["nan"],"p":{}},"1085A":{"i":["nan"],"p":{}},"1085a":{"i":["nan"],"p":{}},"1086":{"i":["nan"],"p":{}},"1086B":{"i":["nan"],"p":{}},"1152":{"i":["nan"],"p":{}},"1153":{"i":["nan"],"p":{}},"123/9XZY":{"i":["nan"],"p":{}},"123/9ZY":{"i":["nan"],"p":{}},"126/9XZY":{"i":["nan"],"p":{}},"131/9ZY":{"i":["nan"],"p":{}},"136/9ZY":{"i":["nan"],"p":{}},"1401":{"i":["nan"],"p":{}},"1501":{"i":["nan"],"p":{}},"1504":{"i":["nan"],"p":{}},"1506":{"i":["nan"],"p":{}},"1511":{"i":["nan"],"p":{}},"1522":{"i":["nan"],"p":{}},"1525":{"i":["nan"],"p":{}},"1526":{"i":["nan"],"p":{}},"1527":{"i":["nan"],"p":{}},"1547":{"i":["nan"],"p":{}},"1550":{"i":["nan"],"p":{}},"1600":{"i":["nan"],"p":{}},"1642":{"i":["nan"],"p":{}},"170/9ZY":{"i":["nan"],"p":{}},"173/9XZY":{"i":["nan"],"p":{}},"173/9ZY":{"i":["nan"],"p":{}},"18/9ZY":{"i":["nan"],"p":{}},"191/9ZY":{"i":["nan"],"p":{}},"2/9XZY":{"i":["nan"],"p":{}},"20/9XZY":{"i":["nan"],"p":{}},"2006":{"i":["nan"],"p":{}},"2034":{"i":["nan"],"p":{}},"2042":{"i":["nan"],"p":{}},"22/9ZY":{"i":["nan"],"p":{}},"2203":{"i":["nan"],"p":{}},"2210":{"i":["nan"],"p":{}},"2221":{"i":["nan"],"p":{}},"2223":{"i":["nan"],"p":{}},"2224":{"i":["nan"],"p":{}},"2227":{"i":["nan"],"p":{}},"2250":{"i":["nan"],"p":{}},"2263":{"i":["nan"],"p":{}},"2271":{"i":["nan"],"p":{}},"29":{"i":["nan"],"p":{}},"300":{"i":["nan"],"p":{}},"305":{"i":["nan"],"p":{}},"33":{"i":["nan"],"p":{}},"350":{"i":["nan"],"p":{}},"358":{"i":["nan"],"p":{}},"360":{"i":["nan"],"p":{}},"38":{"i":["nan"],"p":{}},"38/9XZY":{"i":["nan"],"p":{}},"38A":{"i":["nan"],"p":{}},"39":{"i":["nan"],"p":{}},"46":{"i":["nan"],"p":{}},"50":{"i":["nan"],"p":{}},"500A":{"i":["nan"],"p":{}},"501":{"i":["nan"],"p":{}},"502":{"i":["nan"],"p":{}},"503":{"i":["nan"],"p":{}},"504":{"i":["nan"],"p":{}},"507A":{"i":["nan"],"p":{}},"508":{"i":["nan"],"p":{}},"510A":{"i":["nan"],"p":{}},"512":{"i":["nan"],"p":{}},"514":{"i":["nan"],"p":{}},"515C":{"i":["nan"],"p":{}},"52":{"i":["nan"],"p":{}},"523A":{"i":["nan"],"p":{}},"524A":{"i":["nan"],"p":{}},"530A":{"i":["nan"],"p":{}},"530C":{"i":["nan"],"p":{}},"530D":{"i":["nan"],"p":{}},"530c":{"i":["nan"],"p":{}},"537":{"i":["nan"],"p":{}},"541":{"i":["nan"],"p":{}},"543":{"i":["nan"],"p":{}},"544":{"i":["nan"],"p":{}},"553":{"i":["nan"],"p":{}},"554":{"i":["nan"],"p":{}},"555A":{"i":["nan"],"p":{}},"557":{"i":["nan"],"p":{}},"564":{"i":["nan"],"p":{}},"565A":{"i":["nan"],"p":{}},"570":{"i":["nan"],"p":{}},"576":{"i":["nan"],"p":{}},"582C":{"i":["nan"],"p":{}},"584":{"i":["nan"],"p":{}},"585":{"i":["nan"],"p":{}},"590":{"i":["nan"],"p":{}},"590A":{"i":["nan"],"p":{}},"592":{"i":["nan"],"p":{}},"593":{"i":["nan"],"p":{}},"594":{"i":["nan"],"p":{}},"596A":{"i":["nan"],"p":{}},"597":{"i":["nan"],"p":{}},"599":{"i":["nan"],"p":{}},"600":{"i":["nan"],"p":{}},"601":{"i":["nan"],"p":{}},"603A":{"i":["nan"],"p":{}},"605":{"i":["nan"],"p":{}},"610B":{"i":["nan"],"p":{}},"611":{"i":["nan"],"p":{}},"612":{"i":["nan"],"p":{}},"615":{"i":["nan"],"p":{}},"622":{"i":["nan"],"p":{}},"627C":{"i":["nan"],"p":{}},"631":{"i":["nan"],"p":{}},"650":{"i":["nan"],"p":{}},"651":{"i":["nan"],"p":{}},"660":{"i":["nan"],"p":{}},"665":{"i":["nan"],"p":{}},"667":{"i":["nan"],"p":{}},"67/9XZY":{"i":["nan"],"p":{}},"678":{"i":["nan"],"p":{}},"678B":{"i":["nan"],"p":{}},"68/9XZY":{"i":["nan"],"p":{}},"680B":{"i":["nan"],"p":{}},"681":{"i":["nan"],"p":{}},"682":{"i":["nan"],"p":{}},"686A":{"i":["nan"],"p":{}},"687":{"i":["nan"],"p":{}},"688":{"i":["nan"],"p":{}},"69/9XZY":{"i":["nan"],"p":{}},"7/880XR":{"i":["nan"],"p":{}},"701":{"i":["nan"],"p":{}},"710":{"i":["nan"],"p":{}},"721":{"i":["nan"],"p":{}},"723":{"i":["nan"],"p":{}},"725":{"i":["nan"],"p":{}},"725A":{"i":["nan"],"p":{}},"726":{"i":["nan"],"p":{}},"727":{"i":["nan"],"p":{}},"728":{"i":["nan"],"p":{}},"732":{"i":["nan"],"p":{}},"736":{"i":["nan"],"p":{}},"738B":{"i":["nan"],"p":{}},"74/9XZY":{"i":["nan"],"p":{}},"742":{"i":["nan"],"p":{}},"746":{"i":["nan"],"p":{}},"759B":{"i":["nan"],"p":{}},"763":{"i":["nan"],"p":{}},"772":{"i":["nan"],"p":{}},"773":{"i":["nan"],"p":{}},"782":{"i":["nan"],"p":{}},"785":{"i":["nan"],"p":{}},"791A":{"i":["nan"],"p":{}},"791C":{"i":["nan"],"p":{}},"792":{"i":["nan"],"p":{}},"80/9XZY":{"i":["nan"],"p":{}},"80A/9XZY":{"i":["nan"],"p":{}},"813":{"i":["nan"],"p":{}},"82":{"i":["nan"],"p":{}},"832":{"i":["nan"],"p":{}},"840":{"i":["nan"],"p":{}},"845":{"i":["nan"],"p":{}},"87/9XZY":{"i":["nan"],"p":{}},"870":{"i":["nan"],"p":{}},"872A":{"i":["nan"],"p":{}},"873":{"i":["nan"],"p":{}},"874":{"i":["nan"],"p":{}},"875":{"i":["nan"],"p":{}},"875A":{"i":["nan"],"p":{}},"891C":{"i":["nan"],"p":{}},"893":{"i":["nan"],"p":{}},"896":{"i":["nan"],"p":{}},"900":{"i":["nan"],"p":{}},"901":{"i":["nan"],"p":{}},"903":{"i":["nan"],"p":{}},"931":{"i":["nan"],"p":{}},"95/9XZY":{"i":["nan"],"p":{}},"951":{"i":["nan"],"p":{}},"951A":{"i":["nan"],"p":{}},"97/9XZY":{"i":["nan"],"p":{}},"971":{"i":["nan"],"p":{}},"982":{"i":["nan"],"p":{}},"984":{"i":["nan"],"p":{}},"984B":{"i":["nan"],"p":{}},"985":{"i":["nan"],"p":{}},"986":{"i":["nan"],"p":{}},"99":{"i":["nan"],"p":{}},"99/9ZY":{"i":["nan"],"p":{}},"990":{"i":["nan"],"p":{}},"991":{"i":["nan"],"p":{}},"998":{"i":["nan"],"p":{}},"AH10":{"i":["nan"],"p":{}},"AH100":{"i":["nan"],"p":{}},"AH1004":{"i":["nan"],"p":{}},"AH111":{"i":["nan"],"p":{}},"AH112":{"i":["nan"],"p":{}},"AH137":{"i":["nan"],"p":{}},"AH1525":{"i":["nan"],"p":{}},"AH18":{"i":["nan"],"p":{}},"AH19":{"i":["nan"],"p":{}},"AH20":{"i":["nan"],"p":{}},"AH22":{"i":["nan"],"p":{}},"AH2224":{"i":["nan"],"p":{}},"AH2225":{"i":["nan"],"p":{}},"AH500":{"i":["nan"],"p":{}},"AH501":{"i":["nan"],"p":{}},"AH502":{"i":["nan"],"p":{}},"AH503":{"i":["nan"],"p":{}},"AH510":{"i":["nan"],"p":{}},"AH530":{"i":["nan"],"p":{}},"AH59":{"i":["nan"],"p":{}},"AH600":{"i":["nan"],"p":{}},"AH602":{"i":["nan"],"p":{}},"AH610":{"i":["nan"],"p":{}},"AH611":{"i":["0"],"p":{}},"AH701900711":{"i":["nan"],"p":{}},"AH82":{"i":["nan"],"p":{}},"AH85":{"i":["nan"],"p":{}},"ZY126/9":{"i":["nan"],"p":{}},"ZY170/9":{"i":["nan"],"p":{}},"א.ח 500":{"i":["nan"],"p":{}},"בית מגורים":{"i":["nan"],"p":{}},"בית מטבחיים":{"i":["nan"],"p":{}},"עמוד 1500":{"i":["nan"],"p":{}},"עמוד 2221":{"i":["nan"],"p":{}},"עמוד 988":{"i":["nan"],"p":{}},"תחט\"פ פרלמנט":{"i":["nan"],"p":{}},"דיר אל-אסד 512":{"i":[],"p":{"nan":"1"}}}