{"1 ZL":{"i":[""],"p":{}},"10/54 ST":{"i":[""],"p":{}},"108 ST":{"i":[""],"p":{}},"115 ST":{"i":[""],"p":{}},"14/57 ST":{"i":[""],"p":{}},"196":{"i":[""],"p":{}},"3/1 דA":{"i":[""],"p":{}},"4/45ST":{"i":[""],"p":{}},"5/54 ST":{"i":[""],"p":{}},"61 ST":{"i":[""],"p":{}},"7/134ד":{"i":[""],"p":{}},"71 ST":{"i":[""],"p":{}},"82 ST":{"i":[""],"p":{}},"90 ST":{"i":[""],"p":{}},"97 ST":{"i":[""],"p":{}},"אבן עזרא":{"i":["1","10","11","13","15","17","19","2","3","4","5","6","7","8","9"],"p":{}},"אדר":{"i":["1","10","11","12","13","14","15","16","17","18","19","2","20","21","22","3","4","5","6","7","8","9"],"p":{}},"אהרון צ'חנובר":{"i":["10","11","12","13","14","15","16","17","18","19","20","21","22","23","23א","24","25","27","29","31","33","35","37","39","41","43","4א","5","6","8","9","9א"],"p":{}},"אומן":{"i":["10","4","8"],"p":{}},"אזוב":{"i":["12"],"p":{}},"אזור התעשיה":{"i":["116","138","22","383","401","406B","407A","48","8747","8755","8756","8757","8758","8759","8760","8761","8762","8763","8764","8765","8766","8768","8769","8776"],"p":{}},"אזור התעשיה 1/33 ST":{"i":[""],"p":{}},"אזור התעשיה 10/57 ST":{"i":[""],"p":{}},"אזור התעשיה 25 ST":{"i":[""],"p":{}},"אזור התעשיה 4/45 ST":{"i":[""],"p":{}},"אזור התעשיה 511":{"i":[""],"p":{}},"אזור התעשיה 514":{"i":[""],"p":{}},"אזור התעשיה 516":{"i":[""],"p":{}},"אזור התעשיה 517":{"i":[""],"p":{}},"אזור התעשיה 6/57 ST":{"i":[""],"p":{}},"אזור התעשיה ד 1/75":{"i":[""],"p":{}},"אזור התעשיה ד 1/77":{"i":[""],"p":{}},"אזור התעשיה ד 12/134":{"i":[""],"p":{}},"אזור התעשיה ד 2/134":{"i":[""],"p":{}},"אזור התעשיה ד 2/136":{"i":[""],"p":{}},"אזור התעשיה ד 3/85":{"i":[""],"p":{}},"אזור התעשיה ד 30/77":{"i":[""],"p":{}},"אזור התעשיה ד 303":{"i":[""],"p":{}},"אזור התעשיה ד 8/135":{"i":[""],"p":{}},"אזור התעשיה ד 8/85":{"i":[""],"p":{}},"אזור התעשיה ד 9/134":{"i":[""],"p":{}},"אזור התעשיה ד 9/77":{"i":[""],"p":{}},"אחד העם":{"i":["1","11","12","13","3","5","7","8","9"],"p":{}},"איירין סלא":{"i":["1","3"],"p":{}},"אלה":{"i":["2"],"p":{}},"אלה 1545":{"i":[""],"p":{}},"אלה ד 121/122":{"i":[""],"p":{}},"אלחריזי":{"i":["10","12","14","16","18","20","22","5","7","8","9"],"p":{}},"אמנון ותמר":{"i":["1","11","13","15","17","19","21","23","3","5","7","8","9"],"p":{}},"אסף":{"i":["1","3","5","7"],"p":{}},"אפרסק":{"i":["10","12","14","6","8"],"p":{}},"אקליפטוס":{"i":["1","11","13","15","17","18","19","21","23","25","27","3","31","33","35","37","39","45","47","49","5","51","55","57","59","7","9"],"p":{}},"אקסודוס":{"i":["1","10","11","2","3","4","5","6","7","8","9"],"p":{}},"אשחר":{"i":["1","11","12","13","14","15","16","17","19","2","20","21","24","25","26","27","29","3","31","32","34","37","4","5","6","7","9"],"p":{}},"בבא סאלי":{"i":["1","100","102","104","106","107","108","109","11","110","111","112","114","115","116","118","119","12","120","121","123","125","126","127","129","14","141","142","143","144","145","15","16","18","19","2","20","21","22","23","24","25","26","27","29","3","30","31","32","33","35","36","37","389","39","390","40","41","42","43","44","45","46","47","49","5","62","69","7","70","72","74","76","77","78","79","80","81","82","83","84","85","86","87","88","89","9","90","91","92","93","94","95","96","97","98","99"],"p":{}},"בבא סאלי ד 119":{"i":[""],"p":{}},"בבא סאלי ד 31/119":{"i":[""],"p":{}},"בבא סאלי דA701":{"i":[""],"p":{}},"בוגרשוב":{"i":["2","3","4","5","6","8"],"p":{}},"בית שערים":{"i":["1","10","12","13","14","16","17","17א","18","19","1א","2","20","21","22","23","24","25","26","27","29","2ב","3","30","31","33","34","35","36","38","4","40","5","6","7","8"],"p":{}},"בר כוכבא":{"i":["1","10","12","3","4","5","6","7","8","9"],"p":{}},"ברקן":{"i":["1","10","11","12","13","14","15","16","17","18","19","2","21","23","3","4","5","7","8","9"],"p":{}},"בשמת":{"i":["1","12","13","16","18","2","20","3","4","5","6","7","8","9"],"p":{}},"בת חן":{"i":["1","10","11","12","13","14","15","16","17","18","2","3","4","5","6","7","8","9"],"p":{}},"גולדה מאיר":{"i":["1005","149","150","2","20","6"],"p":{}},"גולדה מאיר ד 145/122":{"i":[""],"p":{}},"גולדה מאיר ד 20/122":{"i":[""],"p":{}},"גולדה מאיר ד 30/122":{"i":[""],"p":{}},"גמלא":{"i":["10","12","13","14","16","17","18","19","20","22","24","25","26","28","2ב","30","32","34","36","4","42","44","45","48","50","54","56","58","6","60","62","64","66","68","70","8"],"p":{}},"גמלא 10/119 T":{"i":[""],"p":{}},"גמלא ד 13/119":{"i":[""],"p":{}},"ד 1/40":{"i":[""],"p":{}},"ד 1/78":{"i":[""],"p":{}},"ד 5/101":{"i":[""],"p":{}},"דבורה הנביאה":{"i":["10","12","14","16","18","22","24","26","28","3","30","32","34","36","38","40","5","6","7"],"p":{}},"דבורה עומר":{"i":["2","3","4","5","6"],"p":{}},"דובדבן":{"i":["1","10","11","12","13","14","15","16","17","18","19","2","20","22","24","26","28","2ציבורי","3","30","32","34","36","4","5","6","7","8","9"],"p":{}},"דוגית":{"i":["10","11","12","13","14","15","16","17","18","19","2","20","21","22","23","24","25","26","27","28","29","3","30","31","32","33","34","35","36","37","38","39","4","40","41","42","43","45","47","49","5","6","7","8","9"],"p":{}},"דוגית ד 1/153":{"i":[""],"p":{}},"דוד אלעזר":{"i":["1161","1162","1163","1164","1165","1166","1167","1171","1172","1173","1174"],"p":{}},"דוכיפת":{"i":["1","10","11","3","5","8","9"],"p":{}},"דולב":{"i":["1","11","19","22"],"p":{}},"דיזינגוף":{"i":["1"],"p":{}},"דיזנגוף":{"i":["11","13","15","17","19","21","23","25","3","4","5","5א","7","9"],"p":{}},"דניאל כהנמן":{"i":["1","10","12","14","15","16","17","18","19","20","23","3","4","5","6","9"],"p":{}},"דפנה":{"i":["10","11","12","13","14","16","17","19","2","21","22","23","24","25","27","29","4","6","8","9"],"p":{}},"דרך בן גוריון":{"i":["11","13","1318","15","16","18","19","21","23","25","27","285","29","31","33","35","37","39","40א","41","43","45","51","54","55","57","59","61","63","65","66","68","69","7","75","81","83","85","87","89","9","91","93","95","97"],"p":{}},"דרך בן גוריון 1324":{"i":[""],"p":{}},"דרך בן גוריון ד 17/122":{"i":[""],"p":{}},"דרך בן גוריון ד 70/122":{"i":[""],"p":{}},"דרך בר לב חיים":{"i":["1"],"p":{}},"דרך בר לב חיים ד 18/122":{"i":[""],"p":{}},"דרך הצנחנים":{"i":["1","10","11","12","13","15","17","19","2","21","23","25","27","3","4","5","6","7","8","9"],"p":{}},"דרך השלום":{"i":["1","10","12","1204","1206","13","14","15","17","18","2","20","21","22","23","24","26","27","28","29","3","31","32","33","34","35","36","37","38","4","40","42","45","46","47","48","49","5","50","51","52","54","55","56","57","61","63","65","69","7","71","73","75","77","79","81","83","9"],"p":{}},"האורן":{"i":["1","10","12","13","14","15","16","2","20","4","5","7","8"],"p":{}},"האיריס":{"i":["2","3","5","7"],"p":{}},"האלון":{"i":["10","12","14","16","18","2","20","22","24","26","28","30","4","6","8"],"p":{}},"האשל":{"i":["10","12","13","14","16","18","2","20","4","5","6","8"],"p":{}},"הברוש":{"i":["10","11","13","15","17","19","21","23","26א","3","4","5","6","7","8","9"],"p":{}},"הגיא":{"i":["10","12","14","16","18","2","20","3","4","5","6","7","8"],"p":{}},"הגפן":{"i":["1","10","11","12","13","14","15","16","17","18","19","2","21","23","25","27","28","29","3","30","31","32","33","34","35","36","37","38","39","4","40","42","43","44","45","46","47","48","49","5","51","6","7","8","9"],"p":{}},"הגפן 460":{"i":[""],"p":{}},"הדרור":{"i":["1","10","12","13","15","16","2","3","5","6","7","9"],"p":{}},"ההדס":{"i":["11","15","17","19","21","23","25","8","9"],"p":{}},"הזית":{"i":["10","11","12","15","17","2","25","27","29","3","33","4","5","6","8"],"p":{}},"הזמיר":{"i":["1","10","12","13","14","15","16","17","18","19","2","21","23","24","26","3","4","5","7","9"],"p":{}},"החורש":{"i":["10","9"],"p":{}},"החיטה":{"i":["2","4","6","8"],"p":{}},"החשמונאים":{"i":["10","4","6","6א","8"],"p":{}},"היונה":{"i":["10","12","14","153","155","16","2","4","6","8"],"p":{}},"היורה":{"i":["1","10","11","12","16","17","18","26","28","3","30","34","36","4"],"p":{}},"הכינור":{"i":["1","10","11","12","13","14","15","16","2","3","4","5","6","7","8","9"],"p":{}},"הכלנית":{"i":["1","10","11","12","13","14","15","16","17","19","20","21","22","23","24","25","26","26א","27","28","29","3","32","34","36","38","40","42","46","5","7","8","9"],"p":{}},"המכבים":{"i":["1","10","11","12","13","14","15","16","18","20","22","24","3","4","5","6","7","8","9"],"p":{}},"המכתש":{"i":["1","10","11","12","14","15","17","18","19","20","21","24","30","32","34","4","5","6","7","8"],"p":{}},"המכתש 62":{"i":[""],"p":{}},"המלאכה":{"i":["12","12א","25","3","31","4","51","52ב","6","8"],"p":{}},"המלך דוד":{"i":["2"],"p":{}},"המעלה":{"i":["1","10","11","12","13","14","15","16","17","18","19","2","20","22","25","26","27","29","3","31","33","4","5","6","7","8","9"],"p":{}},"המעפיל":{"i":["19","22","24","26","28","30","32","34","36","37","38","4","40","41","42","44","45","46","48","4א","50","52","52א","54","56","58","59","60","61","62","63","64","65","66","67","68","69","70","72","73","75","76","77","78","79","80","81","82","83","84","85","86","87","88","90","91","92","94","96","98"],"p":{}},"המעפיל 1455":{"i":[""],"p":{}},"המעפיל ד 18/122":{"i":[""],"p":{}},"המעפיל ד 53/122":{"i":[""],"p":{}},"הנבל":{"i":["10","11","12","13","14","16","18","2","20","28","3","30","32","34","36/1","36/2","36/3","36/4","36/5","36/6","36/7","36/8","36/9","4","40","42","44/1","44/2","44/3","44/4","44/5","44/6","46/1","46/2","46/3","46/4","46/5","46/6","48/1","48/2","48/3","48/4","48/5","48/6","5","6","8"],"p":{}},"הנרי מלכה":{"i":["10","11","12","13","14","16","18","20","22","24","26","28","3","30","32","4","5","6","7","8","9"],"p":{}},"הנרקיס":{"i":["10","11","12","14","16","18","20","24","26","3","4","5","6","7","8","9"],"p":{}},"הסנהדרין":{"i":["1","10","12","14","16","18","2","3","4","5","6","7","8"],"p":{}},"העליה":{"i":["1","10","14","16","18","26","28","30","32","34","38","391","392","393","394","395","396","397","399","40","400","401","402","403","404","405","406","407","408","410","411","412","413","414","416","417","418","419","420","422","423","424","425","426","427","429","430","431","432","433","435","8"],"p":{}},"העליה ד 154":{"i":[""],"p":{}},"העליה ד 162":{"i":[""],"p":{}},"העמל":{"i":["1","1006","3","5","903"],"p":{}},"העצמאות":{"i":["10","1010","1011","1013","12","14","6","8"],"p":{}},"הפועלים":{"i":["15","16","228","26","27","28","29","3","30","33","38","5"],"p":{}},"הפועלים ד 1/78":{"i":[""],"p":{}},"הפסגה":{"i":["1","10","101","103","105","107","109","11","111","113","115","117","119","12","13","14","16","18","19","2","20","22","23","24","25","27","28","29","3","30","31","32","33","34","35","36","37","38","39","4","40","41","42","43","45","47","48","49","5","50","51","53","55","57","58","59","6","60","61","62","63","64","65","66","68","69","7","70","71","72","73","74","76","77","78","79","80","81","82","83","84","85","86","87","88","89","9","90","91","93","95","97","99"],"p":{}},"הצאלה":{"i":["11","13","15","17","6","7","9"],"p":{}},"הצבר":{"i":["10","12","14","16","18","2","20","22","24","26","28","30","32","34","36","38","4"],"p":{}},"הצבר ד B701":{"i":[""],"p":{}},"הר אדיר":{"i":["1","11","3","4","5","6","7","9"],"p":{}},"הר ארבל":{"i":["1","11","12","13","14","15","16","17","18","19","2","20","22","24","25","26","27","28","29","30","30א","31","32","33","34","35","36","37","39","4","41","43","6","7","9"],"p":{}},"הר ארבל פילר 1891":{"i":[""],"p":{}},"הר ארבל פילר 1894":{"i":[""],"p":{}},"הר ארגמן":{"i":["1","10","2","3","4","5","6","8"],"p":{}},"הר גבים":{"i":["1","11","13","14","15","16","17","19","21","23","25","7","9"],"p":{}},"הר גולן":{"i":["1","3","4","5","6","7","9","9א"],"p":{}},"הר גילה":{"i":["1","2","3","4","6","7"],"p":{}},"הר גריזים":{"i":["10","11","12","13","15","2","3","4","5","6","7","8זמני","9"],"p":{}},"הר דב":{"i":["1","10","2","4","5","6","8"],"p":{}},"הר הנגב":{"i":["1/1","1/2","1/3","1/4","10","11","13","14","15","16","18","19","1א","2","20","21","22","23","24","26","28","2א","3/1","3/2","3/3","3/4","3/5","3/6","4","6","7","9"],"p":{}},"הר הצופים":{"i":["1/1","1/10","1/12","1/2","1/3","1/4","1/5","1/6","1/7","1/8","10","14","16","18","2/1","2/2","2/3","2/4","2/5","2/6","2/7","2/8","2א","6","8"],"p":{}},"הר חזון":{"i":["11","13","2","3","4","7","9"],"p":{}},"הר חרוז":{"i":["10","11","12","2","3","4","5","6","7","8","9"],"p":{}},"הר חרמון":{"i":["1","10","11","12","13","14","15","17","3","4","5","7","8","9"],"p":{}},"הר יהל":{"i":["2/1","2/2","2/3","2/4","3"],"p":{}},"הר כנען":{"i":["1","10","11","12","13","2","3","4","5","6","7","8","9"],"p":{}},"הר כפיר":{"i":["1","10","12","13","15","16","17","18","3","5","7"],"p":{}},"הר כרכום":{"i":["1","11","2","3","4","5","6","7","8","9"],"p":{}},"הר כרמל":{"i":["1","10","11","12","13","14","16","17","18","19","20","21","23","25","3","4","5","6","7","8","9"],"p":{}},"הר מוריה":{"i":["1","10","11","12","13","14","15","16","17","18","19","1א","2","20","21","22","23","24","25","26","28","3","30","34","36","38","39","4","41","5","6","7","8","9"],"p":{}},"הר מירון":{"i":["1","10","12","2","3","4","5","6","7","8","9","9א"],"p":{}},"הר נבו":{"i":["1","10","2","3","4","5","6","7","8","9"],"p":{}},"הר נס":{"i":["1","3","4","5"],"p":{}},"הר עצמון":{"i":["1","10","11","13","15","2","3","3א","4","5","7","8","9"],"p":{}},"הר רביד":{"i":["1","11","12","13","14","18","2","6","7","9"],"p":{}},"הר שגיא":{"i":["10","11","12","13","2","3","4","5","6","7","8","9"],"p":{}},"הר שניר":{"i":["1","10","11","12","14","16","18","19","2","2/5","2/6","20","21","23","24","25","26","27","29","3","4","5","6","7","8","9"],"p":{}},"הר תבור":{"i":["1","10","2","3","4","5","6","7","8","9"],"p":{}},"הרב אבוחצירה":{"i":["1307"],"p":{}},"הרב אברהם אלמליח":{"i":["2","3זמני"],"p":{}},"הרב אברהם קוק":{"i":["1","10","11","12","13","14","15","17","19","20","21","22","25א","25ב","25ג","25ד","25ה","25ו'","25משותף","27","28","29","3","30","31","32","34","36","38","4","40","42","44","46","48","5","50","6","7","8","9"],"p":{}},"הרב אלנקוה":{"i":["1316","1317","1319","1323"],"p":{}},"הרב אלנקוה ל 23":{"i":[""],"p":{}},"הרב אלנקווה":{"i":["32"],"p":{}},"הרב אלעזר אבוחצירה":{"i":["10","15","30","4","6","8"],"p":{}},"הרב מרדכי אליהו":{"i":["12","12א","14","16","16א","17זמני","18","1זמני","24","24א","26","28","5זמני"],"p":{}},"הרב עובדיה יוסף":{"i":["17","19","38","40","42","44","46"],"p":{}},"הרבי מלובאויטש":{"i":["1/1","1/10","1/11","1/12","1/13","1/14","1/15","1/16","1/17","1/18","1/19","1/2","1/20","1/21","1/22","1/23","1/24","1/3","1/4","1/5","1/6","1/7","1/8","1/9","13זמני","17","19","20זמני","21","23","23א","24","25","26","27","28","29","29א","30","31","32","33","34","35","35א","36","36א","37","38","4","40","42","44","46","6זמני"],"p":{}},"הרדוף הנחלים":{"i":["17","23"],"p":{}},"הרדיון":{"i":["1","10","11","12","13","14","15","16","17","18","19","20","21","22","23","24","25","26","27","28","29","3","30","31","4","5","6","7","8","9"],"p":{}},"הרימון":{"i":["1","11","12","13","14","15","16","18","19","2","20","22","23","24","34","4","58","6","7","74","8","9"],"p":{}},"הרכס":{"i":["10","11","12","13","14","15","16","17","18","19","2","20","3","4","5","6","7","8","9"],"p":{}},"הרמה":{"i":["1","10","11","12","13","14","15","16","17","18","19","2","20","21","22","23","24","25","26","27","28","29","3","30","31","32","33","34","35","36","37","38","39","4","40","41","42","43","44","44א","45","46","47","48","49","5","50","51","52","53","54","55","56","58","6","60","7","8","9"],"p":{}},"הרמה ד 109/122":{"i":[""],"p":{}},"הרמה פילר 1724":{"i":[""],"p":{}},"הרצל":{"i":["10","101","103","105","107","12א","14א","16","18","19","20","21","22","23","233","24","25","26","27","28","29","31","33","34","35","36","37","38","39","3א","40","41","42","43","44","45","46","47","48","50","52","54","55","56","57","58","59","6","60","61","62","63","64","65","67","69","6א","7","71","73","75","77","79","81","83","85","87","89","8א","91","93","95","97","99"],"p":{}},"הרצל ד 1/77":{"i":[""],"p":{}},"הרצל ד 121":{"i":[""],"p":{}},"הרצל ד 126":{"i":[""],"p":{}},"הרצל ד 141":{"i":[""],"p":{}},"הרקפת":{"i":["11","3","7","9"],"p":{}},"השיא":{"i":["1","10","11","12","13","14","15","16","17","19","2","21","3","4","5","6","7","8","9"],"p":{}},"השיבולים":{"i":["12","26","29","31","38","4","51","53","55","56","58","6","60","62","63","64","66","68","69","71","72","73","75","76","77","78","79","80","81","82","83","85"],"p":{}},"השיבולים 148":{"i":[""],"p":{}},"השיטה":{"i":["10","2","3","4","5","6","8"],"p":{}},"השיריון":{"i":["15","17","7","9"],"p":{}},"השלוה":{"i":["10","12","14","16","2","3","4","6","8"],"p":{}},"השלוה 1554":{"i":[""],"p":{}},"השלוה 1557":{"i":[""],"p":{}},"התאנה":{"i":["1","10","11","12","13","14","15","17","18","19","21","23","24","25","26","27","28","29","3","30","31","32","33","34","35","36","37","38","39","40","42","46","48","49","5","50","54","6","62","7","8","9"],"p":{}},"התפוצות":{"i":["11","13","143","144","145","15","17","19","2","29","31","33","35","37","39","9"],"p":{}},"התפוצות 63/122":{"i":[""],"p":{}},"ורדימון יצחק":{"i":["10","12","14","16","18","20","22","8"],"p":{}},"ורדימון יצחק ד 174":{"i":[""],"p":{}},"ורדימון יצחק ד 175":{"i":[""],"p":{}},"ורדימון יצחק ד 184":{"i":[""],"p":{}},"זויתן":{"i":["3"],"p":{}},"חגי":{"i":["1","10","11","12","13","14","15","16","17","18","19","2","20","21","22","23","24","25","26","27","28","29","3","30","31","32","33","34","35","36","37","38","39","4","40","41","42","43","44","46","48","5","50","52","54","56","58","6","7","8","9"],"p":{}},"חטיבת אלכסנדרוני":{"i":["141","142","2","4"],"p":{}},"חטיבת גולני":{"i":["1","153","154","3"],"p":{}},"חטיבת הנגב":{"i":["1","11","3","5","7","9"],"p":{}},"חטיבת הראל":{"i":["1","3","4","6"],"p":{}},"חמת גדר":{"i":["10","11","12","14","16","18","2","20","22","24","26","28","3","4","5","7","8","9"],"p":{}},"חצב":{"i":["1","11","12","13","15","16","17","18","19","2","20","21","22","24","25","27","29","3","31","33","35","37","39","4","41","43","45","47","49","5","51","53","55","57","59","6","61"],"p":{}},"חרוב":{"i":["1","10","11","12","13","14","15","16","17","18","2","20","21","22","24","25","26","27","29","31","35","36","37","39","4","41","43","45","47","49","5","6","7","8","9"],"p":{}},"חרוב ל 1/29":{"i":[""],"p":{}},"חרצית":{"i":["1","10","11","12","13","14","15","16","17","19","2","21","3","4","5","6","7","8","9"],"p":{}},"טופח":{"i":["1","10","11","12","13","14","15","16","17","18","19","20","21","22","23","24","25","26","27","28","29","3","30","31","32","33","34","35","37","39","4","6","7","8","9"],"p":{}},"טיילת הספורט":{"i":["10","12","14א","16","22","24","26","28","30","38","4","40","42","44","46","6","8"],"p":{}},"יגור":{"i":["10","11","12","13","14","15","16","17","19","2","21","25","27","29","31","33","35","37","39","4","41","43","45","6","8"],"p":{}},"יהודה הלוי":{"i":["1","11","13","15","17","19","2","21","23","25","27","29","29א","3","31","33","35","37","39","4","5","7","9"],"p":{}},"יואל":{"i":["6"],"p":{}},"יודפת":{"i":["10","11","12","13","14","16","17","18","19","20","22","24","26","3","4","5","6","7","8","9"],"p":{}},"יוסף קארו":{"i":["1","11","13","15","2","3","4","5","6","7","9"],"p":{}},"יוסף קארו 93/122 T":{"i":[""],"p":{}},"יצחק בשביס זינגר":{"i":["6"],"p":{}},"יצחק שדה":{"i":["10","6"],"p":{}},"יציאת אירופה":{"i":["2","4"],"p":{}},"ירמיה":{"i":["10","12","14","15","16","18","20","22","24","25","26","28","3","30","32","34","38","4","40","5","6","8"],"p":{}},"ירמיה פילר 1792":{"i":[""],"p":{}},"ישעיה":{"i":["10","11","12","13","14","15","16","17","18","19","20","21","23","25","26","27","28","3","30","32","34","36","38","4","40","42","44","46","48","50","52","54","6","8","9"],"p":{}},"ישראל אומן":{"i":["1","10","11","11א","13","17","18","19","2","21","22","23","24","25","26","27","27א","29","3","31","33","35","37","39","4","41","43","5","6","7","8","9"],"p":{}},"כביש דימונה ירוחם רם 9/30":{"i":[""],"p":{}},"כובשי אילת":{"i":["11","12","14","24","26","28","2א","3","32","33","34","35","36","38","39","4","40","41","43","6","7","9"],"p":{}},"כובשי אילת 339":{"i":[""],"p":{}},"כובשי אילת 355":{"i":[""],"p":{}},"כובשי אילת ד 3/107":{"i":[""],"p":{}},"כורזין":{"i":["10","11","12","13","14","15","16","17","18","20","22","23","24","25","26","27","28","29","30","32","34","36","5","6","8"],"p":{}},"כליל החורש":{"i":["1","11","13","15","17","19","21","23","25","26","27","29","3","30","31","33","35","37","39","4","41","42","43","45","47","49","5","51","52","6","7","9"],"p":{}},"ליבנה":{"i":["10","12","14","16","18","2","20","22","24","26","28","30","32","34","36","38","4","40","42","44","46","48","50","52","6","8"],"p":{}},"לילינבלום":{"i":["11","13","15","17","21","23","23א","5","5א","6","7","8","9"],"p":{}},"לילך":{"i":["1","10","12","14","16","18","2","20","22","24","26","4","5","6","8"],"p":{}},"מ\"ג המעפילים":{"i":["10","11","12","13","14","15","15א","16","17","17א","2","20","22","24","26","28","28ב","30","32","34","36","4","6","8","9"],"p":{}},"מ\"ג המעפילים 191":{"i":[""],"p":{}},"מבצע ברוש":{"i":["1","10","2","3","4","5","6","7","8","9"],"p":{}},"מבצע דני":{"i":["3","5","7","9"],"p":{}},"מבצע חורב":{"i":["10","12","14","16","2","4","8"],"p":{}},"מבצע יואב":{"i":["1","11","3","5","7","9"],"p":{}},"מבצע עובדה":{"i":["1","11","13","3","5","7"],"p":{}},"מבצר עכו":{"i":["1","10","11","12","13","14","15","17","20","21","22","23","25","26","27","3","5","6","7","8","9"],"p":{}},"מודיעין":{"i":["1","2","3","4"],"p":{}},"מולדה":{"i":["12","14","16","18","2","38","4","40","42","44","46"],"p":{}},"מונפור":{"i":["10","12","14","16","18","2","20","22","24","26","28","30","32","34","36","4","6","8"],"p":{}},"מורג":{"i":["10","11","12","13","14","15","16","17","2","3","4","5","6","7","8","9"],"p":{}},"מורן החורש":{"i":["1","11","13","14","15","16","18","2","20","22","24","3","4","42","5","50","51","56","6","7","8","9"],"p":{}},"מילרוד אליעזר":{"i":["10","14","16","2","4","8"],"p":{}},"מלאכי":{"i":["1","2","3","4"],"p":{}},"מלכי ישראל":{"i":["53"],"p":{}},"מצדה":{"i":["1","11","14","21","24","26","28","3","30","32","34","6","7"],"p":{}},"מצדה 13A":{"i":[""],"p":{}},"מרווה":{"i":["13","17","19","2","4","7"],"p":{}},"מרחבים":{"i":["1","1210","1302","1303","1304","1305","132","1320","1321","1322","1327","1328","1329","133","1330","1331","1332","3","46","48","5","52","66","68","7","70","72","74","76","78"],"p":{}},"מרים הנביאה":{"i":["1","11","2","3","4","5","6","7","9"],"p":{}},"משה דיין":{"i":["2","6","8"],"p":{}},"משעול ארז":{"i":["2","4","6","8"],"p":{}},"משעול ההגנה":{"i":["10","12","2","4","6","8"],"p":{}},"משעול החירות":{"i":["1","10","11","2","3","4","6","7","8","9"],"p":{}},"משעול הרעות":{"i":["1308","1310","1312"],"p":{}},"משעול התקומה":{"i":["1","10","11","12","2","3","4","5","6","7","8","9"],"p":{}},"משעול חירם":{"i":["10","11","12","2","4","5","6","7","8","9"],"p":{}},"משעול רגבים":{"i":["1","15","3","5","7","9"],"p":{}},"משעול רוגל":{"i":["11","13","15","17","19","5","7","9"],"p":{}},"משעול שלדג":{"i":["1","10","11","12","13","16","4","5","6","8"],"p":{}},"מתתיהו הכהן":{"i":["1","10","12","14","16","18","2","20","22","24","26","3","4","5","6","7","7א","8","9"],"p":{}},"נבטים":{"i":["1","10","12","13","14","16","2","3","4","5","6","8","9"],"p":{}},"נוה מדבר":{"i":["10","11","12","13","15","17","18","20","21","22","23","25","26","27","28","29","30","31","32","33","34","35","37","38","4","40","41","42","43","44","46","47","48","49","50","51","54","56","58","6","60","62","7","8"],"p":{}},"נורית":{"i":["1","11","18","20","6"],"p":{}},"נחום":{"i":["1","2","3","5","7","9"],"p":{}},"נחלת בנימין":{"i":["2","3","4","5","6","7"],"p":{}},"נטעים":{"i":["1","10","11","12","14","15","16","3","4","5","6","7","8","9"],"p":{}},"ניצנה":{"i":["1","2","3","4","5","6","8"],"p":{}},"נצרים":{"i":["1","11","3","5","7","9"],"p":{}},"נתיב הל\"ה":{"i":["1","10","11","12","14","16","2","3","4","5","6","7","8","9"],"p":{}},"נתיב הצפורים":{"i":["1"],"p":{}},"נתן הנביא":{"i":["2","4"],"p":{}},"סא\"ל עמנואל מורנו":{"i":["1","10זמני","13","15","15א","17","19","19א","20","20א","21","22","24","26","26א","28","7"],"p":{}},"סחלבן החורש":{"i":["1","10","11","12","13","14","15","16","17","18","19","2","20","21","22","23","26","3","38","47","5","51","54","68","7","8","9"],"p":{}},"סטרומה ד 97/122":{"i":[""],"p":{}},"סיגלון":{"i":["10","12","14","16","18","2","20","22","24","26","28","4","6","8"],"p":{}},"סיתונית":{"i":["1","10","11","12","13","14","16","18","19","20","21","22","23","25","27","29","3","4","5","6","7","8","9"],"p":{}},"סרן יובל נריה":{"i":["13זמני","2","4","6","8"],"p":{}},"סרן עודד אמיר":{"i":["10","11","12","13","14","15","16","17","18","19","2","20","21","22","23","24","26","4","7","8","9"],"p":{}},"עבדת":{"i":["10","11","12","14","17","18","19","2","21","22","23","24","25","27","28","29","3","31","33","35","37","45","47","49","51","53","55","7","8"],"p":{}},"עבדת 425":{"i":[""],"p":{}},"עדה יונת":{"i":["13ב","13ג","13ד","13ה","13ו","17ב","17ג"],"p":{}},"עולי הגרדום":{"i":["10","11","12","13","15","17","19","2","21","25","27","29","3","31","33","35","4","5","6","7","8","9"],"p":{}},"עזרא ונחמיה":{"i":["1","10","12","14","16","19","21","23","25","27","3","4","5","6","7","8","9"],"p":{}},"עזרא ונחמיה ד 159":{"i":[""],"p":{}},"עיינות":{"i":["1","2","4"],"p":{}},"עין גדי":{"i":["1","3","4","5","7"],"p":{}},"עמוד 1/135T":{"i":[""],"p":{}},"עמוד 16/135T":{"i":[""],"p":{}},"עמוד 66/122ד":{"i":[""],"p":{}},"עמוד 7530T":{"i":[""],"p":{}},"עמוד ד6/135":{"i":[""],"p":{}},"עמוד ל18":{"i":[""],"p":{}},"עמוד רם 1/15":{"i":[""],"p":{}},"עמוד רם 2/15":{"i":[""],"p":{}},"עמוס":{"i":["1","2","3","4","6"],"p":{}},"ערוגות":{"i":["1","12","13","14","16","2","4","5","8"],"p":{}},"ערוגות 1328":{"i":[""],"p":{}},"פטרה":{"i":["10","11","12","13","14","15","17","18","19","2","20","21","22","23","24","26","3","4","5","6","8"],"p":{}},"פקיעין":{"i":["1","10","11","12","13","14","15","16","17","18","19","2","20","21","22","23","24","25","27","3","4","5","6","7","8","9"],"p":{}},"פרג":{"i":["1","11","13","15","17","19","2","20","21","23","25","26","27","29","3","9"],"p":{}},"פרופ' דן שכטמן":{"i":["1","10","11","11א","12","13","14","15","16","17","19","2","21","23","23א","25","27","29","3","31","33","35","37","39","4","41","43","45","5","6","7","8","9"],"p":{}},"פרופסור עדה יונת":{"i":["1","10","12","13","13א","14","15","15א","16","18","1א","20","21","23","25","27","3","4","5","7"],"p":{}},"פרחי ארצנו":{"i":["29","6"],"p":{}},"פרץ סנטר":{"i":["1"],"p":{}},"צבעוני":{"i":["1","14","5"],"p":{}},"צורית":{"i":["13","14","18","20"],"p":{}},"ציפורי":{"i":["1","10","11","12","13","14","15","16","17","18","19","20","21","22","23","25","27","29","3","31","33","35","39","43","45","47","49","5","51","53","55","57","59","61","63","65","67","69","7","8","9"],"p":{}},"ציפורן":{"i":["1","11","13","15","16","17","19","23","25","27","29","3","31","33","35","42","5","7","9"],"p":{}},"ציפורן פילר 1842/2/1":{"i":[""],"p":{}},"צפצפה":{"i":["12","13"],"p":{}},"קדש":{"i":["10","15","16","17","18","20","21","23","25","26","27","28","29","3","31","4","5","6","8"],"p":{}},"קדש 64":{"i":[""],"p":{}},"קהילת בריטניה":{"i":["139","140"],"p":{}},"קהלני אביגדור":{"i":["10","10א","12","14","16","18","18א","20","22","24","26","26א","28","30","32","34","34א","36","38","40","42","42א","44","46","48"],"p":{}},"קהלני אביגדור תט\"פ נויה ל71/5":{"i":[""],"p":{}},"קומראן":{"i":["10","11","12","13","14","15","16","17","18","19","2","20","21","22","23","24","25","26","27","28","29","3","30","31","32","33","35","37","4","5","6","7","8","9"],"p":{}},"קטלב":{"i":["11","13","15","17","19","21","23","25","27","29","3","31","33","35","37","39","41","43","45","47","5","7","9"],"p":{}},"קיסריה":{"i":["10","11","12","13","14","15","16","17","18","19","2","20","21","22","24","4","5","6","7","8","9"],"p":{}},"קלעת נמרוד":{"i":["1","11","13","15","17","19","21","23","25","27","29","3","31","33","35","37","5","7","9"],"p":{}},"קציעות":{"i":["10","11","13","14","3","4","5","631","633","634","637","7","8","9"],"p":{}},"קצרין":{"i":["1","11","13","15","17","21","23","25","27","3","5","7","9"],"p":{}},"קרני חיטין":{"i":["1","10","11","12","13","14","15","16","18","19","2","20","21","22","23","24","25","26","28","3","30","32","34","36","38","4","40","42","5","6","8","9"],"p":{}},"ר.שמעון בר יוחאי":{"i":["2","4"],"p":{}},"ר.שמעון בר יוחאי ד 113/122":{"i":[""],"p":{}},"רבי נחמן מאומן":{"i":["10","11א","12","14","16","18","1זמני","20","22","4","6","8"],"p":{}},"רוטשילד":{"i":["10","11","12","12א","14","14א","16","18","18א","2","20","22","24","24א","26","6","6א","8","9"],"p":{}},"רזיאל דוד":{"i":["1","10","12","16","18","2","20","22","26","28","3","4","5","6","7","8","9"],"p":{}},"רזיאל דוד ד 2/138":{"i":[""],"p":{}},"רחבת אורון":{"i":["10","11","12","13","14","4","5","6","8","9"],"p":{}},"רחבת האיסיים":{"i":["1","10","11","12","13","14","15","17","2","3","4","5","6","7","8","9"],"p":{}},"רחבת האיסיים 255":{"i":[""],"p":{}},"רחבת האצ\"ל":{"i":["4","6"],"p":{}},"רחבת האשלג":{"i":["10","11","13","15","16","18","19","21","23","25","27","29","3","4","5","6","8"],"p":{}},"רחבת ההגנה":{"i":["1","10","12","14","16","18","2","20","22","28","3","30","32","34","4","5","6","7","8"],"p":{}},"רחבת ההגנה 1693":{"i":[""],"p":{}},"רחבת הלח\"י":{"i":["1","10","12","14","2","3","4","5","6","7","8","9"],"p":{}},"רחבת הנח\"ל":{"i":["146","147","148","151","152"],"p":{}},"רחבת הפלמ\"ח":{"i":["1","11","13","15","17","19","2","3","4","5","6","9"],"p":{}},"רחבת הפלמ\"ח ד 3/173":{"i":[""],"p":{}},"רחבת הרב טייב":{"i":["905"],"p":{}},"רחבת הרמבם":{"i":["1324","1325","1326"],"p":{}},"רחבת הרמבם 1582":{"i":[""],"p":{}},"רחבת יונתן":{"i":["27","28","29"],"p":{}},"רחבת שאול המלך":{"i":["3"],"p":{}},"רם 34/30":{"i":[""],"p":{}},"שבטה":{"i":["1","10","11","12","13","15","17","19","21","23","25","3","4","5","7","9"],"p":{}},"שד אריאל שרון":{"i":["1","10","101","103","105","107","109","111","113","115","15","17","19","20","23","24","25","26","27","28","29","30","31","32","33","34","35","36","37","39","4","41","41א","42","43","44","45","46","47","49","51","53","54","55","56","57","59","6","60","61","61א","62","63","65","66","67","69","71","73","75","77","79","8","81","83","87","89","91"],"p":{}},"שד הנשיא ד 91":{"i":[""],"p":{}},"שד יגאל אלון":{"i":["10","11","110","12","13","14","15","16","17","18","19","2","20","21","22","23","24","25","26","27","28","29","30","31","32","33","34","35","36","37","38","39","4","40","41","42","43","44","45","47","48","49","5","51","52","53","56","58","6","60","72","74","8","84","86","8א","94"],"p":{}},"שד יגאל אלון ד 102":{"i":[""],"p":{}},"שד' ירושלים":{"i":["10","12","14","16","18","22","24","26","28","30","32","34","36","38","40","42","46","48","50","52","54","56","58","6","60","62","8"],"p":{}},"שדה יצחק":{"i":["1","18א","2","4","6","8"],"p":{}},"שושן צחור":{"i":["1","10","12","13","14","16","18","2","20","22","24","26","28","3","4","5","6","7","8","9"],"p":{}},"שטרן יאיר":{"i":["1"],"p":{}},"שיזף":{"i":["100","102","104","106","108","110","112","114","116","118","120","122","124","126","130","132","134","136","138","140","142","144","146","162","24","52","54","56","58","60","61","62","63","64","66","68","70","71","72","74","76","78","80","82","84","86","88","90","92","94","96"],"p":{}},"שיזף פילר 1845":{"i":[""],"p":{}},"שיקמה":{"i":["1","10","11","12","13","14","15","16","17","18","19","2","20","21","22","23","24","25","26","28","3","30","32","34","36","4","5","6","7","7א","8","9"],"p":{}},"שלום שבזי":{"i":["1","10","11","12","13","14","15","16","17","18","19","2","20","22","24","26","28","3","30","32","34","36","38","4","40","42","44","46","5","6","7","8","9"],"p":{}},"שלמה אבן גבירול":{"i":["1","10","11","12","13","14","15","16","17","18","19","2","20","21","22","23","24","25","26","27","28","29","3","30","31","32","33","34","35","36","37","39","4","41","43","45","47","49","5","51","6","7","8","9"],"p":{}},"שמואל יוסף עגנון":{"i":["1","10","11","12","13","14","15","16","17","19","2","20","21","22","23משותף","3","33","35","37","4","43","5","6","7","8","9","9 זמני"],"p":{}},"תל אפק":{"i":["10","11","12","13","14","15","16","17","18","2","20","21","22","24","25","26","27","28","2א","3","30","32","34","36","38","4","40","42","44","46","48","5","50","52","6","7","8","9"],"p":{}},"תל אפק 14/119 T":{"i":[""],"p":{}},"תל גבעון":{"i":["10","12","14","16","16א","18","20","20א","22","24","24א","25","26","3","5","52זמני","6","8"],"p":{}},"תל דן":{"i":["1","3"],"p":{}},"תל חמה":{"i":["10","11","12","13","14","15","16","17","18","19","1א","1ב","20","21","22","23","24","25","27","29","3","31","33","35","5","6","7","8","9"],"p":{}},"תל לכיש":{"i":["1","10","12","12א","14","18","2","20","22","24","26","28","2א","3","4","8"],"p":{}},"תל ערד":{"i":["1","10","11","12","13","14","15","16","17","19","2","20","21","22","24","25","27","28","29","3","30","31","32","5","6","7","8","9"],"p":{}},"תל פורן":{"i":["5"],"p":{}}}