{"1013/313QU":{"i":[""],"p":{}},"15":{"i":[""],"p":{}},"1פ 513/313QU":{"i":[""],"p":{}},"321/313QU":{"i":[""],"p":{}},"453/313/QU":{"i":[""],"p":{}},"508/3138QU":{"i":[""],"p":{}},"508/313QU":{"i":[""],"p":{}},"510/313XQU":{"i":[""],"p":{}},"511/313QU":{"i":[""],"p":{}},"517/313QU":{"i":[""],"p":{}},"517/313XUQ":{"i":[""],"p":{}},"519/313XQU":{"i":[""],"p":{}},"553/313/QU":{"i":[""],"p":{}},"AH5811":{"i":[""],"p":{}},"AH5812":{"i":[""],"p":{}},"AH5815":{"i":[""],"p":{}},"AH5820":{"i":[""],"p":{}},"AH5825":{"i":["2561"],"p":{}},"AH5826":{"i":[""],"p":{}},"AH5873 מגורים":{"i":["126"],"p":{}},"UQ313/125":{"i":[""],"p":{}},"UQ313/225":{"i":[""],"p":{}},"יונתן":{"i":["104","109","113","117","118","119","12","14","143","145","147","150","151","154","155","157","159","17","21","30","39","40","43","5","55","6","66","74","77","78","86","87","88","89","90","94","95","97","99"],"p":{"144":"1","149":"1","110":"1","114":"1","115":"1","117":"1","119":"1","113":"1","143":"1","146":"1","147":"1"}},"יונתן AH5812":{"i":[],"p":{"":"1"}},"יונתן יונתן AH5812":{"i":[],"p":{"":"1"}},"יונתן QU511/313":{"i":[],"p":{"":"1"}},"יונתן 15":{"i":[],"p":{"":"4"}}}