{"1/473T":{"i":[""],"p":{}},"10/42HD":{"i":[""],"p":{}},"10/473T":{"i":[""],"p":{}},"1001":{"i":[""],"p":{}},"11":{"i":[""],"p":{}},"110":{"i":[""],"p":{}},"116/473XT":{"i":[""],"p":{}},"126/473T":{"i":[""],"p":{}},"14":{"i":[""],"p":{}},"142/473T":{"i":[""],"p":{}},"145/473T":{"i":[""],"p":{}},"151":{"i":[""],"p":{}},"158":{"i":[""],"p":{}},"16":{"i":[""],"p":{}},"160":{"i":[""],"p":{}},"160/473T":{"i":[""],"p":{}},"161":{"i":[""],"p":{}},"163":{"i":[""],"p":{}},"164":{"i":[""],"p":{}},"165":{"i":[""],"p":{}},"171":{"i":[""],"p":{}},"171/473XT":{"i":[""],"p":{}},"173/473T":{"i":[""],"p":{}},"174/473XT":{"i":[""],"p":{}},"175B":{"i":[""],"p":{}},"176":{"i":[""],"p":{}},"177/473T":{"i":[""],"p":{}},"181/473T":{"i":[""],"p":{}},"184":{"i":[""],"p":{}},"2":{"i":[""],"p":{}},"2/437T":{"i":[""],"p":{}},"210/473T":{"i":[""],"p":{}},"22/473T":{"i":[""],"p":{}},"235":{"i":[""],"p":{}},"241":{"i":[""],"p":{}},"251":{"i":[""],"p":{}},"263":{"i":[""],"p":{}},"265":{"i":[""],"p":{}},"294":{"i":[""],"p":{}},"32/23QN":{"i":[""],"p":{}},"320":{"i":[""],"p":{}},"341":{"i":[""],"p":{}},"350":{"i":[""],"p":{}},"4/473XT":{"i":[""],"p":{}},"455":{"i":[""],"p":{}},"457":{"i":[""],"p":{}},"4B":{"i":[""],"p":{}},"501T":{"i":[""],"p":{}},"528Y":{"i":[""],"p":{}},"543Y":{"i":[""],"p":{}},"552Y":{"i":[""],"p":{}},"565Y":{"i":[""],"p":{}},"57":{"i":[""],"p":{}},"6":{"i":[""],"p":{}},"63/473XT":{"i":[""],"p":{}},"64":{"i":[""],"p":{}},"64/473T":{"i":[""],"p":{}},"65":{"i":[""],"p":{}},"717Y":{"i":[""],"p":{}},"718XY":{"i":[""],"p":{}},"729Y":{"i":[""],"p":{}},"75/473T":{"i":[""],"p":{}},"77/473T":{"i":[""],"p":{}},"8/473T":{"i":[""],"p":{}},"81":{"i":[""],"p":{}},"82":{"i":[""],"p":{}},"82/473XT":{"i":[""],"p":{}},"85":{"i":[""],"p":{}},"86":{"i":[""],"p":{}},"87":{"i":[""],"p":{}},"88":{"i":[""],"p":{}},"91/473XT":{"i":[""],"p":{}},"AH6501":{"i":[""],"p":{}},"AH6511":{"i":[""],"p":{}},"AH6515":{"i":[""],"p":{}},"AH6517":{"i":[""],"p":{}},"AH6520":{"i":[""],"p":{}},"AH6540":{"i":[""],"p":{}},"AH6551":{"i":[""],"p":{}},"AH6552":{"i":[""],"p":{}},"AH6553":{"i":[""],"p":{}},"AH6560":{"i":[""],"p":{}},"AH6570":{"i":[""],"p":{}},"AH6580":{"i":[""],"p":{}},"AH6590":{"i":[""],"p":{}},"א.ח.0056":{"i":[""],"p":{}},"גולן":{"i":["1","18"],"p":{}},"דרך הבוסתן 164":{"i":[""],"p":{}},"דרך הבוסתן 165":{"i":[""],"p":{}},"האגם":{"i":["10","12","2","36","4","6"],"p":{}},"האגם 203":{"i":[""],"p":{}},"האגם AH6530":{"i":[""],"p":{}},"האלונים":{"i":["2","3","6"],"p":{}},"האשכולות":{"i":["5","8"],"p":{}},"הבוסתן":{"i":[""],"p":{}},"הבוסתן 162":{"i":[""],"p":{}},"הגפן":{"i":["18","20","21","33"],"p":{}},"הזית":{"i":["10"],"p":{}},"המיסדים":{"i":["10","4","9"],"p":{}},"המיסדים AH6510":{"i":[""],"p":{}},"הראשונים":{"i":["2","7"],"p":{}},"הרחבה ה":{"i":["104","107","108","112","122","132","133","136","18"],"p":{}},"הרחבה ה 321":{"i":[""],"p":{}},"הרחבה ה 92/473XT":{"i":[""],"p":{}},"הרימונים":{"i":["33","36","37"],"p":{}},"השקד":{"i":["","1","11","20"],"p":{}},"חע 52/2":{"i":[""],"p":{}},"חע15/2":{"i":[""],"p":{}},"חע56":{"i":[""],"p":{}},"יסוד המעלה":{"i":["1","10","203","25","26","38","62","7","74"],"p":{"203":"4"}},"יסוד המעלה 159":{"i":[""],"p":{}},"יסוד המעלה 162":{"i":[""],"p":{}},"יסוד המעלה 192":{"i":[""],"p":{}},"יסוד המעלה 232":{"i":[""],"p":{}},"יסוד המעלה 62/473XT":{"i":[""],"p":{}},"יסוד המעלה 63/473XT":{"i":[""],"p":{}},"יסוד המעלה 64/473XT":{"i":[""],"p":{}},"יסוד המעלה AH6511":{"i":[""],"p":{}},"מושבה AH6514":{"i":[""],"p":{}},"מי חולה":{"i":[""],"p":{}},"עמוד  37/473T":{"i":[""],"p":{}},"עמוד ***":{"i":[""],"p":{}},"עמוד 1/473T":{"i":[""],"p":{}},"עמוד 140":{"i":[""],"p":{}},"עמוד 156":{"i":[""],"p":{}},"עמוד 164":{"i":[""],"p":{}},"קניון":{"i":[""],"p":{}},"רסקו":{"i":["1","12","13","14","15","16","17","18","19","22","25","28","3","4","5","6","7","8","9"],"p":{}},"רסקו 12":{"i":[""],"p":{}},"רסקו 18":{"i":[""],"p":{}},"רסקו 20":{"i":[""],"p":{}},"רסקו 21":{"i":[""],"p":{}},"רסקו 22":{"i":[""],"p":{}},"רסקו 23":{"i":[""],"p":{}},"רסקו 28":{"i":[""],"p":{}},"רסקו 37/473XT":{"i":[""],"p":{}},"רסקו 53":{"i":[""],"p":{}},"רסקו 55":{"i":[""],"p":{}},"רסקו 6":{"i":[""],"p":{}},"רסקו 80/473XT":{"i":[""],"p":{}},"רסקו 81/473XT":{"i":[""],"p":{}},"רסקו 82/473XT":{"i":[""],"p":{}},"תט\"פ קניון 6054*":{"i":[""],"p":{}},"יסוד המעלה Y552":{"i":[],"p":{"":"1"}}}