{"1/295F":{"i":["nan"],"p":{}},"1/539H":{"i":["nan"],"p":{}},"1000":{"i":["nan"],"p":{}},"1006":{"i":["nan"],"p":{}},"102":{"i":["nan"],"p":{}},"1022":{"i":["nan"],"p":{}},"103":{"i":["nan"],"p":{}},"104":{"i":["nan"],"p":{}},"106":{"i":["nan"],"p":{}},"107":{"i":["nan"],"p":{}},"107A":{"i":["nan"],"p":{}},"108/548H":{"i":["nan"],"p":{}},"110":{"i":["nan"],"p":{}},"111":{"i":["nan"],"p":{}},"112":{"i":["nan"],"p":{}},"115":{"i":["nan"],"p":{}},"116":{"i":["nan"],"p":{}},"117":{"i":["nan"],"p":{}},"121":{"i":["nan"],"p":{}},"122":{"i":["nan"],"p":{}},"123":{"i":["nan"],"p":{}},"124":{"i":["nan"],"p":{}},"125":{"i":["nan"],"p":{}},"134":{"i":["nan"],"p":{}},"144":{"i":["nan"],"p":{}},"146":{"i":["nan"],"p":{}},"150":{"i":["nan"],"p":{}},"1500":{"i":["nan"],"p":{}},"152/548XH":{"i":["nan"],"p":{}},"153":{"i":["nan"],"p":{}},"153/548H":{"i":["nan"],"p":{}},"154/548H":{"i":["nan"],"p":{}},"154/548XH":{"i":["nan"],"p":{}},"155/548H":{"i":["nan"],"p":{}},"158":{"i":["nan"],"p":{}},"17":{"i":["nan"],"p":{}},"171/548XH":{"i":["nan"],"p":{}},"180/548H":{"i":["nan"],"p":{}},"182":{"i":["nan"],"p":{}},"19":{"i":["nan"],"p":{}},"190/548H":{"i":["nan"],"p":{}},"2/311F":{"i":["nan"],"p":{}},"2/548H":{"i":["nan"],"p":{}},"21/314F":{"i":["nan"],"p":{}},"21/548H":{"i":["nan"],"p":{}},"210/548H":{"i":["nan"],"p":{}},"214":{"i":["nan"],"p":{}},"22":{"i":["nan"],"p":{}},"235":{"i":["nan"],"p":{}},"236":{"i":["nan"],"p":{}},"262":{"i":["nan"],"p":{}},"263":{"i":["nan"],"p":{}},"272":{"i":["nan"],"p":{}},"288":{"i":["nan"],"p":{}},"290":{"i":["nan"],"p":{}},"3/314F":{"i":["nan"],"p":{}},"303F":{"i":["nan"],"p":{}},"314":{"i":["nan"],"p":{}},"315":{"i":["nan"],"p":{}},"316":{"i":["nan"],"p":{}},"321":{"i":["nan"],"p":{}},"324":{"i":["nan"],"p":{}},"34/548/H":{"i":["nan"],"p":{}},"350":{"i":["nan"],"p":{}},"351B":{"i":["nan"],"p":{}},"43/548H":{"i":["nan"],"p":{}},"43A":{"i":["nan"],"p":{}},"44":{"i":["nan"],"p":{}},"45":{"i":["nan"],"p":{}},"48":{"i":["nan"],"p":{}},"49":{"i":["nan"],"p":{}},"52":{"i":["nan"],"p":{}},"53":{"i":["nan"],"p":{}},"54":{"i":["nan"],"p":{}},"546H":{"i":["nan"],"p":{}},"55":{"i":["nan"],"p":{}},"56":{"i":["nan"],"p":{}},"57":{"i":["nan"],"p":{}},"59":{"i":["nan"],"p":{}},"6/314/F":{"i":["nan"],"p":{}},"60":{"i":["nan"],"p":{}},"604":{"i":["nan"],"p":{}},"61":{"i":["nan"],"p":{}},"62":{"i":["nan"],"p":{}},"63":{"i":["nan"],"p":{}},"64":{"i":["nan"],"p":{}},"65":{"i":["nan"],"p":{}},"66":{"i":["nan"],"p":{}},"67":{"i":["nan"],"p":{}},"68":{"i":["nan"],"p":{}},"69":{"i":["nan"],"p":{}},"7/313F":{"i":["nan"],"p":{}},"70":{"i":["nan"],"p":{}},"700":{"i":["nan"],"p":{}},"701":{"i":["nan"],"p":{}},"706":{"i":["nan"],"p":{}},"707":{"i":["nan"],"p":{}},"708":{"i":["nan"],"p":{}},"71":{"i":["nan"],"p":{}},"710":{"i":["nan"],"p":{}},"711":{"i":["nan"],"p":{}},"730":{"i":["nan"],"p":{}},"733":{"i":["nan"],"p":{}},"735":{"i":["nan"],"p":{}},"741":{"i":["nan"],"p":{}},"747":{"i":["nan"],"p":{}},"75":{"i":["nan"],"p":{}},"76":{"i":["nan"],"p":{}},"80":{"i":["nan"],"p":{}},"82":{"i":["nan"],"p":{}},"83":{"i":["nan"],"p":{}},"85":{"i":["nan"],"p":{}},"850":{"i":["nan"],"p":{}},"88":{"i":["nan"],"p":{}},"89":{"i":["nan"],"p":{}},"9/297F":{"i":["nan"],"p":{}},"91":{"i":["nan"],"p":{}},"92":{"i":["nan"],"p":{}},"96":{"i":["nan"],"p":{}},"960":{"i":["nan"],"p":{}},"964":{"i":["nan"],"p":{}},"98":{"i":["nan"],"p":{}},"99":{"i":["nan"],"p":{}},"AH2347":{"i":["nan"],"p":{}},"א.ח 1":{"i":["nan"],"p":{}},"א.ח 845/571":{"i":["nan"],"p":{}},"גשר הצבים א.ח 2380":{"i":["nan"],"p":{}},"דוגית":{"i":["12","16","18","19","22","3","4","7"],"p":{}},"דרך החול":{"i":["41","43","50"],"p":{}},"דרך הכפר":{"i":["108","125","126","137","139א'","141","142","143","148","149","150","62","66","69","71","72","74","75","76","77","80"],"p":{}},"הבאר":{"i":["107","3","80","82","83","84","86"],"p":{}},"הבאר 76":{"i":["nan"],"p":{}},"הדואר":{"i":["1","102"],"p":{}},"הדואר 1500":{"i":["nan"],"p":{}},"הזנב":{"i":["51א","52","54","55","56"],"p":{}},"הזנב 91":{"i":["nan"],"p":{}},"הלגונה":{"i":["14","16","17","18","22","6"],"p":{}},"המגדלור":{"i":["1","10","12","5","8"],"p":{}},"המחלבה":{"i":["111","112","113","119","122","123ב"],"p":{}},"המפרץ":{"i":["16","2"],"p":{}},"המפרש":{"i":["11","3","5"],"p":{}},"הסיפון":{"i":["3","5","9"],"p":{}},"הסירה":{"i":["11","12","8"],"p":{}},"העוגן":{"i":["1","2","4","5"],"p":{}},"הצדף":{"i":["3","8"],"p":{}},"הקונכיה":{"i":["10","3","4","7","8"],"p":{}},"הראשונים":{"i":["37","88א","88ב","88ג"],"p":{}},"השונית":{"i":["3","4","5"],"p":{}},"ויתקין-1":{"i":["nan","nan"],"p":{}},"ויתקין-2":{"i":["nan"],"p":{}},"כפר ויתקין":{"i":["1","1001","1003","1005","1006","1007","1008","1010","1011","1013","1015","1016","1019","1020","1022","1024","1025","1027","1030","1031","1032","1033","1035","1036","1038","1039","1041","1043","1044","1045","1047","1050","1051","1052","1053","1054","1055","1057","1058","105א","106","1060","1061","1063","1064","1065","1067","1068","1069","1076","1080","1081","1082","1083","1085","1086","1088","109","1091","1095","1096","1098","1100","1101","1102","1107","1109","1110","1112","1115","1116","1117","1118","1120","1121","1122","1123","1125","1126","1127","1128","1131","1135","1136","1138","1140","1141","1142","1143","1144","1145","1146","1147","1149","119א","123","123ד","128","148","2","23","37","38","4","43","43ב","58","59א","76ב","78","8","81","83","85","88","88ב","88ה","8ב","9","91","92","94","97"],"p":{}},"כפר ויתקין 58":{"i":["nan"],"p":{}},"לגונה":{"i":["3","7","8"],"p":{}},"מול הים":{"i":["1","15","23","36","38א","39","6"],"p":{}},"מזח":{"i":["11","13","14","17","4","5","9"],"p":{}},"מחשבי השקיה עמ 196/548H":{"i":["nan"],"p":{}},"משעול הפרדסים":{"i":["88","90","95","96","97","98"],"p":{}},"משעול הפרדסים 21":{"i":["nan"],"p":{}},"מתחם אחסנה עמ 304F":{"i":["nan"],"p":{}},"סמטת הכ\"ג":{"i":["41ד"],"p":{}},"עמ' 105":{"i":["nan"],"p":{}},"עמוד 103":{"i":["nan"],"p":{}},"עמוד 113":{"i":["nan"],"p":{}},"עמוד 174/548H":{"i":["nan"],"p":{}},"עמוד 2/297F לול 5":{"i":["nan"],"p":{}},"עמוד 2/297F לולים":{"i":["nan"],"p":{}},"עמוד 22":{"i":["nan"],"p":{}},"עמוד 290 סככה":{"i":["nan"],"p":{}},"עמוד 314":{"i":["nan"],"p":{}},"עמוד 34/548H":{"i":["nan"],"p":{}},"עמוד 730 רפת":{"i":["nan"],"p":{}},"עמוד 731 מכון חליבה":{"i":["nan"],"p":{}},"קונכיה":{"i":["1"],"p":{}},"רפת עמוד 44/548H":{"i":["nan"],"p":{}}}