{"1064/577R":{"i":["nan"],"p":{}},"226 T":{"i":["nan"],"p":{}},"227 T":{"i":["nan"],"p":{}},"298 T":{"i":["nan"],"p":{}},"9/64LE":{"i":["nan"],"p":{}},"מסעף גילת עק 2/29":{"i":["nan"],"p":{}},"קרית החינוך צ 1/5":{"i":["nan"],"p":{}},"מאמרחבים עמוד T16/220":{"i":[],"p":{"nan":"3"}},"מאמרחבים 227 T":{"i":[],"p":{"nan":"3"}},"מאמרחבים מסעף גילת עק 2/29":{"i":[],"p":{"nan":"3"}},"מאמרחבים עמוד T2/220":{"i":[],"p":{"nan":"3"}},"מאמרחבים ליד עמוד T1/229":{"i":[],"p":{"nan":"3"}},"מאמרחבים 225 T":{"i":[],"p":{"nan":"3"}}}