{"106HA":{"i":[""],"p":{}},"132AH":{"i":[""],"p":{}},"15":{"i":[""],"p":{}},"33":{"i":[""],"p":{}},"35":{"i":[""],"p":{}},"40":{"i":[""],"p":{}},"51":{"i":[""],"p":{}},"56":{"i":[""],"p":{}},"58":{"i":[""],"p":{}},"71":{"i":[""],"p":{}},"95":{"i":[""],"p":{}},"AH100":{"i":[""],"p":{}},"AH110":{"i":[""],"p":{}},"AH120":{"i":[""],"p":{}},"AH121":{"i":[""],"p":{}},"AH133":{"i":[""],"p":{}},"AH134":{"i":[""],"p":{}},"א.ח 106":{"i":[""],"p":{}},"א.ח 110":{"i":[""],"p":{}},"א.ח 111":{"i":[""],"p":{}},"א.ח 112":{"i":[""],"p":{}},"א.ח 132 הרחבה":{"i":["103"],"p":{}},"א.ח.111":{"i":[""],"p":{}},"מנות":{"i":["101","102","104","106","32","4","44","48","49","5","71"],"p":{"44":"2","48":"2","49":"2","51":"2","39":"2","47":"2","43":"2","33":"2","50":"2","46":"2","34":"2","35":"2","18":"2","1":"2","3":"2","4":"2","17":"2","5":"2","38":"2","32":"2","10":"2","2":"2","":"2"}},"עמוד 34":{"i":[""],"p":{}},"מנות AH133":{"i":[],"p":{"":"2"}},"מנות 33":{"i":[],"p":{"":"2"}},"מנות 2":{"i":[],"p":{"":"2"}},"מנות 39":{"i":[],"p":{"":"2"}},"מנות 36":{"i":[],"p":{"":"2"}},"מנות 30":{"i":[],"p":{"":"2"}},"מנות R82/276":{"i":[],"p":{"":"2"}},"מנות מקלט 6":{"i":[],"p":{"":"2"}},"מנות AH100":{"i":[],"p":{"":"2"}},"מנות 91":{"i":[],"p":{"":"2"}},"מנות MC37":{"i":[],"p":{"":"2"}},"מנות 95":{"i":[],"p":{"":"2"}},"מנות הרחבת מנות מגרש 168":{"i":[],"p":{"":"2"}},"מנות AH105":{"i":[],"p":{"":"2"}},"מנות AH110":{"i":[],"p":{"":"2"}},"מנות הרחבת מנות מגרש 164":{"i":[],"p":{"":"2"}},"מנות הרחבת מנות מגרש 145":{"i":[],"p":{"":"2"}},"מנות אח111":{"i":[],"p":{"":"2"}},"מנות הרחבת מנות מגרש 148":{"i":[],"p":{"":"2"}},"מנות AH120":{"i":[],"p":{"":"2"}},"מנות HA106":{"i":[],"p":{"":"2"}},"מנות הרחבת מנות מגרש 158":{"i":[],"p":{"":"2"}},"מנות הרחבת מנות מגרש 165":{"i":[],"p":{"":"2"}},"מנות הרחבת מנות מגרש 139":{"i":[],"p":{"":"2"}},"מנות AH106":{"i":[],"p":{"":"2"}}}