{"115/81G":{"i":["nan"],"p":{}},"223":{"i":["nan"],"p":{}},"32/81 G":{"i":["nan"],"p":{}},"ג":{"i":["nan"],"p":{}},"היוגב":{"i":["210"],"p":{}},"מבנה לוגיסטיקה":{"i":["nan"],"p":{}},"משגב דב":{"i":["1","10","11","12","13","14","141","142","143","144","145","146","147","149","14ב","15","150","151","152","153","154","155","156","157","158","159","16","160","161","162","163","164","166","167","168","169","17","170","171","172","173","174","18","19","1א","2","20","201","203","204","205","206","207","208","209","21","211","212","214","215","216","217","218","219","22","220","221","222","223","224","225","226","227","228","229","23","230","231","232","233","234","235","236","237","238","239","23א","23ב","23ג","24","240","25","26","27","28","29א","29ב","3","30","31","31א","32","35","36","37","38","39","40","41","42","43","44","44א","45","46","46א","47","48","49","5","50","51","52","52א","53","54","56","57","58","59","6","60","61","62","65","74","74א","75ב","76א","76ב","77","77א","78א","78ב","79","79א","8","80","80א","81","9"],"p":{}},"משגב דב מול משק .93":{"i":["nan"],"p":{}},"משגב דב מול משק 78":{"i":["nan"],"p":{}},"משגב דב צמוד למגרש 216":{"i":["nan"],"p":{}},"משק 42":{"i":["nan"],"p":{}},"רח' הרימון ליד הצרכניה":{"i":["nan"],"p":{}}}