{"29":{"i":[""],"p":{}},"31/217":{"i":[""],"p":{}},"35":{"i":[""],"p":{}},"9":{"i":[""],"p":{}},"אתר משותף לפלאפון":{"i":[""],"p":{}},"אתר פלאפון":{"i":[""],"p":{}},"הרחבה":{"i":["10","107","12","13","14","15","16","17","18","19","20","2001","2003","2005","2006","21","22","23","245","25","256","27","28","29","3","30","31","32","33","34","36","37","38","39","4","40","41","42","43","44","46","47","48","49","51","52","53","54","55","57","58","59","6","61","62","63","64","65","68","71","72","73","74","8"],"p":{}},"הרחבה מרכזית תאורה":{"i":[""],"p":{}},"חיבור מרכזיות":{"i":[""],"p":{}},"חיבור ספק":{"i":[""],"p":{}},"מאגד בזק קלסטר 733":{"i":[""],"p":{}},"מעון יום":{"i":[""],"p":{}},"משק 9 מושב נחלה":{"i":[""],"p":{}},"נחלה":{"i":["1","10","101","103","11","12","13","14","15","158","15א","16","17","19","2","20","2002א","21","22","23","24","25","26","27","275","28","30א","31","31א","32","33","35","36","36א","38","39","39א","41","42","43","43א","44","44א","45ב","46","47","48","4ב","4ג","5","50","51","52","53","54","54א","55","56","57","58","59","5א","60","61","62","63","64","65","66","67","69","6א","7","70","72א","73","75א","76","77","78","8","82","83א"],"p":{}},"נחלה מחסן/מחלבה לשעבר":{"i":[""],"p":{}},"נחלה תא שאיבה ראשי":{"i":[""],"p":{}},"תא שומר 353":{"i":[""],"p":{}},"תל אספי - מחסנים":{"i":[""],"p":{}}}