{"1/156XG":{"i":[""],"p":{}},"1/49XBS":{"i":[""],"p":{}},"1/52BS":{"i":[""],"p":{}},"2/176 G":{"i":[""],"p":{}},"20/52BS":{"i":[""],"p":{}},"25/221XBS":{"i":[""],"p":{}},"27/52XBS":{"i":[""],"p":{}},"52XBS":{"i":[""],"p":{}},"56XBS":{"i":[""],"p":{}},"61/221XBS":{"i":[""],"p":{}},"AH1":{"i":[""],"p":{}},"רשפים":{"i":["1","117","124","130","132","133","134","135","136","137","138","139","143","145","147","148","149","150","225","226","227","228","229","234","235","236","237","239","240","241","245","247","248","249","257","258","277"],"p":{}}}